llama_index/packs/searchain/BUILD
llama_index/packs/searchain/__init__.py
llama_index/packs/searchain/base.py
llama_index_packs_searchain-0.3.0.dist-info/METADATA
llama_index_packs_searchain-0.3.0.dist-info/WHEEL
llama_index_packs_searchain-0.3.0.dist-info/RECORD
